pytorch_nlp_pipeline/__init__.py
pytorch_nlp_pipeline/classification.py
pytorch_nlp_pipeline/text_clf.py
pytorch_nlp_pipeline/utils.py
pytorch_nlp_pipeline/data/__init__.py
pytorch_nlp_pipeline/dataset/__init__.py
pytorch_nlp_pipeline/dataset/core.py
pytorch_nlp_pipeline/dataset/utils.py
pytorch_nlp_pipeline/model/__init__.py
pytorch_nlp_pipeline-0.1.12.dist-info/LICENSE.txt
pytorch_nlp_pipeline-0.1.12.dist-info/METADATA
pytorch_nlp_pipeline-0.1.12.dist-info/WHEEL
pytorch_nlp_pipeline-0.1.12.dist-info/top_level.txt
pytorch_nlp_pipeline-0.1.12.dist-info/RECORD
